plugin_commands/__init__.py
one_cli_plugin_commands-0.1.5.dist-info/LICENSE
one_cli_plugin_commands-0.1.5.dist-info/METADATA
one_cli_plugin_commands-0.1.5.dist-info/WHEEL
one_cli_plugin_commands-0.1.5.dist-info/top_level.txt
one_cli_plugin_commands-0.1.5.dist-info/RECORD
